b1_tool/__init__.py
b1_tool/jwt.py
bigone_tool-0.0.1.dist-info/LICENSE
bigone_tool-0.0.1.dist-info/METADATA
bigone_tool-0.0.1.dist-info/WHEEL
bigone_tool-0.0.1.dist-info/top_level.txt
bigone_tool-0.0.1.dist-info/RECORD
